[
  {
    "domain": "drouet-peinture-44654532.fr",
    "chosenAt": "2025-11-17T19:39:23.071Z"
  },
  {
    "domain": "test.co",
    "chosenAt": "2025-11-18T07:06:38.290Z"
  },
  {
    "domain": "bjbjhbhj.fr",
    "chosenAt": "2025-11-18T09:06:44.675Z"
  },
  {
    "domain": "rire.fr",
    "chosenAt": "2025-11-18T09:14:36.330Z"
  },
  {
    "domain": "amouuur.com",
    "chosenAt": "2025-11-18T09:46:12.134Z"
  },
  {
    "domain": "nana44.com",
    "chosenAt": "2025-11-18T09:53:35.645Z"
  },
  {
    "domain": "testonsca.fr",
    "chosenAt": "2025-11-18T12:48:34.903Z"
  },
  {
    "domain": "example-test123.fr",
    "chosenAt": "2025-11-18T12:49:58.197Z"
  },
  {
    "domain": "example-test123.fr",
    "localPart": "contact",
    "chosenAt": "2025-11-18T12:54:13.520Z"
  },
  {
    "domain": "testonk.fr",
    "localPart": "test",
    "chosenAt": "2025-11-18T12:55:50.396Z"
  },
  {
    "domain": "jeteste.io",
    "localPart": "test",
    "chosenAt": "2025-11-18T14:18:35.759Z"
  },
  {
    "domain": "test.co",
    "localPart": "dernier",
    "chosenAt": "2025-11-18T17:27:16.221Z"
  },
  {
    "domain": "tessst.net",
    "localPart": "deeeeeeeeeeeeeeeeeeeeeeeeeeeeeeeeeeeeeeeeeeeejhhhhhhhhhhhhhhhhhhhhhhhhiuuuuuuuuuuuuuuuu",
    "chosenAt": "2025-11-19T12:32:43.032Z"
  },
  {
    "domain": "test.co",
    "localPart": "jjojjjjjjjjjjjjjjjjjjjjjjjjjjjjjjjjjjjjjjjjjjjjjjjjjjjjjjjjjjjjjjjjjjjjjjjjjjjjjjj",
    "chosenAt": "2025-11-19T12:51:30.889Z"
  },
  {
    "domain": "rire.fr",
    "localPart": "g",
    "clientEmail": null,
    "chosenAt": "2025-11-22T01:22:18.133Z"
  },
  {
    "domain": "example.co",
    "requestedDomain": "example.com",
    "localPart": "contact",
    "clientEmail": "test@example.com",
    "chosenAt": "2025-11-23T16:32:56.608Z",
    "hasExistingDomain": "no",
    "displayName": "Test Sender",
    "comment": "Test webhook run",
    "fullName": "Test User",
    "company": "Test Co"
  },
  {
    "domain": "example.co",
    "requestedDomain": "example.com",
    "localPart": "contact",
    "clientEmail": "test@example.com",
    "chosenAt": "2025-11-23T16:33:22.689Z",
    "hasExistingDomain": "no",
    "displayName": "Test Sender",
    "comment": "Test webhook run",
    "fullName": "Test User",
    "company": "Test Co"
  },
  {
    "domain": "example.co",
    "requestedDomain": "example.com",
    "localPart": "contact",
    "clientEmail": "test@example.com",
    "chosenAt": "2025-11-23T16:34:17.516Z",
    "hasExistingDomain": "no",
    "displayName": "Test Sender",
    "comment": "Test webhook run",
    "fullName": "Test User",
    "company": "Test Co"
  },
  {
    "domain": "example.co",
    "requestedDomain": "example.com",
    "localPart": "contact",
    "clientEmail": "test@example.com",
    "chosenAt": "2025-11-23T16:34:54.012Z",
    "hasExistingDomain": "no",
    "displayName": "Test Sender",
    "comment": "Test webhook run",
    "fullName": "Test User",
    "company": "Test Co"
  },
  {
    "domain": "example.co",
    "requestedDomain": "example.com",
    "localPart": "contact",
    "clientEmail": "test@example.com",
    "chosenAt": "2025-11-23T16:42:14.149Z",
    "hasExistingDomain": "no",
    "displayName": "Test Sender",
    "comment": "Test webhook run",
    "fullName": "Test User",
    "company": "Test Co"
  },
  {
    "domain": "example.co",
    "requestedDomain": "example.com",
    "localPart": "contact",
    "clientEmail": "test@example.com",
    "chosenAt": "2025-11-23T16:42:35.060Z",
    "hasExistingDomain": "no",
    "displayName": "Test Sender",
    "comment": "Test webhook run",
    "fullName": "Test User",
    "company": "Test Co"
  },
  {
    "domain": "test-able.fr",
    "requestedDomain": "testable.fr",
    "localPart": "test",
    "clientEmail": "test@testons.com",
    "chosenAt": "2025-11-23T16:50:16.447Z",
    "hasExistingDomain": "no",
    "displayName": "test",
    "comment": null,
    "fullName": "test",
    "company": "testons"
  },
  {
    "domain": "testab-ility.com",
    "requestedDomain": "testability.col",
    "localPart": "test",
    "clientEmail": "test@testons.com",
    "chosenAt": "2025-11-23T16:56:52.595Z",
    "hasExistingDomain": "no",
    "displayName": "test",
    "comment": null,
    "fullName": "test",
    "company": "testons"
  },
  {
    "domain": "test-test.co",
    "requestedDomain": "testtest.fr",
    "localPart": "test",
    "clientEmail": "test@testons.com",
    "chosenAt": "2025-11-23T16:59:42.759Z",
    "hasExistingDomain": "no",
    "displayName": "test",
    "comment": null,
    "fullName": "test",
    "company": "testons"
  },
  {
    "domain": "tets.fr",
    "requestedDomain": "tets.fr",
    "localPart": "test",
    "clientEmail": "test@testons.com",
    "chosenAt": "2025-11-23T17:15:32.937Z",
    "hasExistingDomain": "no",
    "displayName": "test",
    "comment": null,
    "fullName": "test",
    "company": "testons"
  },
  {
    "domain": "testons.co",
    "requestedDomain": "testons.com",
    "localPart": "test",
    "clientEmail": "test@testons.com",
    "chosenAt": "2025-11-23T18:11:30.387Z",
    "hasExistingDomain": "no",
    "displayName": "test",
    "comment": null,
    "fullName": "test",
    "company": "testons"
  },
  {
    "domain": "cvav.co",
    "requestedDomain": "cvav.fr",
    "localPart": "test",
    "clientEmail": "test@testons.com",
    "chosenAt": "2025-11-23T19:58:32.733Z",
    "hasExistingDomain": "no",
    "displayName": "test",
    "comment": null,
    "fullName": "test",
    "company": "testons"
  },
  {
    "domain": "test.co",
    "requestedDomain": "test.co",
    "localPart": "test",
    "clientEmail": "test@testons.com",
    "chosenAt": "2025-11-23T20:02:45.140Z",
    "hasExistingDomain": "no",
    "displayName": "test",
    "comment": null,
    "fullName": "test",
    "company": "testons"
  },
  {
    "domain": "test.co",
    "requestedDomain": "test.fr",
    "localPart": "test",
    "clientEmail": "juliendurant015@gmail.com",
    "chosenAt": "2025-11-25T18:15:24.342Z",
    "hasExistingDomain": "no",
    "displayName": "test",
    "comment": null,
    "fullName": "test",
    "company": "testons"
  },
  {
    "domain": "test.co",
    "requestedDomain": "test.fr",
    "localPart": "test",
    "clientEmail": "juliendurant015@gmail.com",
    "chosenAt": "2025-11-25T19:09:01.210Z",
    "hasExistingDomain": "no",
    "displayName": "test",
    "comment": null,
    "fullName": "test",
    "company": "testons",
    "sessionId": null
  },
  {
    "domain": "example.fr",
    "requestedDomain": "example.fr",
    "localPart": "contact",
    "clientEmail": "webhook-test@example.com",
    "chosenAt": "2025-11-25T19:11:04.423Z",
    "hasExistingDomain": "no",
    "displayName": "Test Sender",
    "comment": null,
    "fullName": "Webhook Test",
    "company": "Test Co",
    "sessionId": "manual-check-1"
  },
  {
    "domain": "test.co",
    "requestedDomain": "test.fr",
    "localPart": "test",
    "clientEmail": "agencevoxety@gmail.com",
    "chosenAt": "2025-11-25T19:16:50.500Z",
    "hasExistingDomain": "no",
    "displayName": "test",
    "comment": null,
    "fullName": "test",
    "company": "testons",
    "sessionId": null
  },
  {
    "domain": "test.co",
    "requestedDomain": "test.fr",
    "localPart": "test",
    "clientEmail": "messagerie.entreprise111@gmail.com",
    "chosenAt": "2025-11-25T19:19:24.816Z",
    "hasExistingDomain": "no",
    "displayName": "test",
    "comment": null,
    "fullName": "test",
    "company": "test",
    "sessionId": null
  },
  {
    "domain": "example.fr",
    "requestedDomain": "example.fr",
    "localPart": "contact",
    "clientEmail": "webhook2@example.com",
    "chosenAt": "2025-11-25T19:20:23.575Z",
    "hasExistingDomain": "no",
    "displayName": "Test Sender",
    "comment": null,
    "fullName": "Test Webhook 2",
    "company": "Test Co",
    "sessionId": "cli-check-2"
  },
  {
    "domain": "example.fr",
    "requestedDomain": "example.fr",
    "localPart": "contact",
    "clientEmail": "webhook-new@example.com",
    "chosenAt": "2025-11-25T19:24:43.510Z",
    "hasExistingDomain": "no",
    "displayName": "Test Sender",
    "comment": null,
    "fullName": "Test Webhook new",
    "company": "Test Co",
    "sessionId": "cli-check-new"
  },
  {
    "domain": "example.fr",
    "requestedDomain": "example.fr",
    "localPart": "contact",
    "clientEmail": "webhook-log@example.com",
    "chosenAt": "2025-11-25T19:25:53.065Z",
    "hasExistingDomain": "no",
    "displayName": "Test Sender",
    "comment": null,
    "fullName": "Test Webhook log",
    "company": "Test Co",
    "sessionId": "cli-check-log"
  },
  {
    "domain": "example.fr",
    "requestedDomain": "example.fr",
    "localPart": "contact",
    "clientEmail": "sheet5-backend@example.com",
    "chosenAt": "2025-11-25T19:45:13.659Z",
    "hasExistingDomain": "no",
    "displayName": "Test Sender",
    "comment": null,
    "fullName": "Test Backend Sheet 5",
    "company": "Test Co",
    "sessionId": "cli-check-sheet5"
  },
  {
    "domain": "example.fr",
    "requestedDomain": "example.fr",
    "localPart": "contact",
    "clientEmail": "sheet-direct@example.com",
    "chosenAt": "2025-11-25T19:54:35.376Z",
    "hasExistingDomain": "no",
    "displayName": "Test Sender",
    "comment": null,
    "fullName": "Sheet Direct Test",
    "company": "Test Co",
    "sessionId": "cli-direct-1"
  },
  {
    "domain": "example.fr",
    "requestedDomain": "example.fr",
    "localPart": "contact",
    "clientEmail": "log-check@example.com",
    "chosenAt": "2025-11-25T20:00:29.590Z",
    "hasExistingDomain": "no",
    "displayName": "Test Sender",
    "comment": null,
    "fullName": "Log Check",
    "company": "Test Co",
    "sessionId": "cli-log-check"
  },
  {
    "domain": "example.fr",
    "requestedDomain": "example.fr",
    "localPart": "contact",
    "clientEmail": "sheet-relay@example.com",
    "chosenAt": "2025-11-25T20:04:38.536Z",
    "hasExistingDomain": "no",
    "displayName": "Test Sender",
    "comment": null,
    "fullName": "Sheet Relay Test",
    "company": "Test Co",
    "sessionId": "cli-relay-1"
  },
  {
    "domain": "example.fr",
    "requestedDomain": "example.fr",
    "localPart": "contact",
    "clientEmail": "sheet-final@example.com",
    "chosenAt": "2025-11-25T20:51:30.485Z",
    "hasExistingDomain": "no",
    "displayName": "Test Sender",
    "comment": null,
    "fullName": "Sheet Final Test",
    "company": "Test Co",
    "sessionId": "cli-final-1"
  },
  {
    "domain": "example.fr",
    "requestedDomain": "example.fr",
    "localPart": "contact",
    "clientEmail": "sheet-final2@example.com",
    "chosenAt": "2025-11-25T20:52:26.470Z",
    "hasExistingDomain": "no",
    "displayName": "Test Sender",
    "comment": null,
    "fullName": "Sheet Final Test",
    "company": "Test Co",
    "sessionId": "cli-final-2"
  },
  {
    "domain": "test.co",
    "requestedDomain": "test.com",
    "localPart": "test",
    "clientEmail": "test@testons.com",
    "chosenAt": "2025-11-25T20:53:45.833Z",
    "hasExistingDomain": "no",
    "displayName": "juliendurant015@gmail.com",
    "comment": null,
    "fullName": "test",
    "company": "testons",
    "sessionId": null
  },
  {
    "domain": "tesp.io",
    "requestedDomain": "tesp.com",
    "localPart": "test",
    "clientEmail": "nerdynerdy923@gmail.com",
    "chosenAt": "2025-11-25T21:03:03.550Z",
    "hasExistingDomain": "no",
    "displayName": "test",
    "comment": null,
    "fullName": "test",
    "company": "testons",
    "sessionId": null
  },
  {
    "domain": "rorororor.fr",
    "requestedDomain": "rorororor.fr",
    "localPart": "azerty",
    "clientEmail": "voxetoagency@gmail.com",
    "chosenAt": "2025-11-25T22:00:02.022Z",
    "hasExistingDomain": "no",
    "displayName": "azertyuiop",
    "comment": null,
    "fullName": "test",
    "company": "test",
    "sessionId": null
  },
  {
    "domain": "test.co",
    "requestedDomain": "test.fr",
    "localPart": "test",
    "clientEmail": "juliendurant015@gmail.com",
    "chosenAt": "2025-11-25T23:13:04.188Z",
    "hasExistingDomain": "no",
    "displayName": "test",
    "comment": null,
    "fullName": "test",
    "company": "testons",
    "sessionId": null
  },
  {
    "domain": "agec.io",
    "requestedDomain": "agec.com",
    "localPart": "agec",
    "clientEmail": "agencevoxety@gmail.com",
    "chosenAt": "2025-11-26T00:02:45.339Z",
    "hasExistingDomain": "no",
    "displayName": "agec",
    "comment": null,
    "fullName": "test",
    "company": "testons",
    "sessionId": null
  },
  {
    "domain": "jujj.de",
    "requestedDomain": "jujj.de",
    "localPart": "juju",
    "clientEmail": "juliendurant015@gmail.com",
    "chosenAt": "2025-12-03T20:04:51.564Z",
    "hasExistingDomain": "no",
    "displayName": "test",
    "comment": null,
    "fullName": "test",
    "company": "ye",
    "sessionId": null
  },
  {
    "domain": "test.co",
    "requestedDomain": "test.fr",
    "localPart": "dernier",
    "clientEmail": "derniertest@gmail.com",
    "chosenAt": "2025-12-04T19:30:07.582Z",
    "hasExistingDomain": "no",
    "displayName": "Dernier Test",
    "comment": null,
    "fullName": "Dernier",
    "company": "Test",
    "sessionId": null
  }
]